[
  {
    "name": "SilkSpawners",
    "url": "https://github.com/timbru31/SilkSpawners/releases/download/silkspawners-7.1.1/SilkSpawners.jar",
    "extradirs": []
  },
  {
    "name": "EssentialsX",
    "url": "https://github.com/EssentialsX/Essentials/releases/download/2.18.2/EssentialsX-2.18.2.0.jar",
    "extradirs": []
  },
  {
    "name": "BlockLocker",
    "url": "https://github.com/rutgerkok/BlockLocker/releases/download/v1.10.1/BlockLocker.jar",
    "extradirs": []
  },
  {
    "name": "Lasso",
    "jar": "Lasso-1.4.1.jar",
    "extradirs": []
  }
]
